AUTHORS
LICENSE
MANIFEST.in
README.rst
setup.py
src/restible_django/__init__.py
src/restible_django/endpoint.py
src/restible_django/resource.py
src/restible_django.egg-info/PKG-INFO
src/restible_django.egg-info/SOURCES.txt
src/restible_django.egg-info/dependency_links.txt
src/restible_django.egg-info/requires.txt
src/restible_django.egg-info/top_level.txt
src/tests/__init__.py
src/tests/settings.py
src/tests/test_routing.py
src/tests/endpoint/__init__.py
src/tests/endpoint/test_dispatch.py
src/tests/endpoint/test_extract_request_data.py