Metadata-Version: 1.1
Name: restible-django
Version: 0.1.1
Summary: Django integration for restible library
Home-page: http://github.com/novopl/restible-django
Author: Mateusz 'novo' Klos
Author-email: novopl@gmail.com
License: MIT
Keywords: restible REST restapi rest server
Platform: UNKNOWN
Classifier: Development Status :: 4 - Beta
Classifier: Topic :: Utilities
Classifier: Intended Audience :: Developers
Classifier: Programming Language :: Python
Classifier: License :: OSI Approved :: MIT License
